prance/__init__.py
prance/_version.py
prance/cli.py
prance/convert.py
prance/mixins.py
prance/util/__init__.py
prance/util/exceptions.py
prance/util/formats.py
prance/util/fs.py
prance/util/iterators.py
prance/util/path.py
prance/util/resolver.py
prance/util/translator.py
prance/util/url.py
prance-23.6.21.0.dist-info/LICENSE.txt
prance-23.6.21.0.dist-info/METADATA
prance-23.6.21.0.dist-info/WHEEL
prance-23.6.21.0.dist-info/entry_points.txt
prance-23.6.21.0.dist-info/top_level.txt
prance-23.6.21.0.dist-info/zip-safe
prance-23.6.21.0.dist-info/RECORD
