Metadata-Version: 2.1
Name: prance
Version: 23.6.21.0
Summary: Resolving Swagger/OpenAPI 2.0 and 3.0.0 Parser
Home-page: https://github.com/RonnyPfannschmidt/prance
Author: Jens Finkhaeuser
Author-email: jens@finkhaeuser.de
Maintainer: Ronny Pfannschmidt
Maintainer-email: opensource@ronnypfannschmidt.de
License: MITNFA
Keywords: swagger openapi parsing
Classifier: Development Status :: 4 - Beta
Classifier: Environment :: Plugins
Classifier: Intended Audience :: Developers
Classifier: License :: OSI Approved :: MIT License
Classifier: Natural Language :: English
Classifier: Operating System :: OS Independent
Classifier: Programming Language :: Python :: 3
Classifier: Programming Language :: Python :: 3.6
Classifier: Programming Language :: Python :: 3.7
Classifier: Programming Language :: Python :: 3.8
Classifier: Topic :: Internet :: WWW/HTTP
Classifier: Topic :: Software Development :: Libraries :: Python Modules
Requires-Python: >=3.8
Provides-Extra: dev
Provides-Extra: icu
Provides-Extra: ssv
Provides-Extra: osv
Provides-Extra: flex
Provides-Extra: cli
License-File: LICENSE.txt
